scrapy/__init__.pyi
types_scrapy-0.1.0.dist-info/METADATA
types_scrapy-0.1.0.dist-info/WHEEL
types_scrapy-0.1.0.dist-info/top_level.txt
types_scrapy-0.1.0.dist-info/RECORD
